beanstalk_dispatch/__init__.py
beanstalk_dispatch/client.py
beanstalk_dispatch/common.py
beanstalk_dispatch/execution.py
beanstalk_dispatch/safe_task.py
beanstalk_dispatch/urls.py
beanstalk_dispatch/views.py
beanstalk_dispatch/tests/__init__.py
beanstalk_dispatch/tests/test_client.py
beanstalk_dispatch/tests/test_dispatcher.py
beanstalk_dispatch/tests/test_safe_task.py
beanstalk_dispatch-0.1.4.dist-info/LICENSE
beanstalk_dispatch-0.1.4.dist-info/METADATA
beanstalk_dispatch-0.1.4.dist-info/WHEEL
beanstalk_dispatch-0.1.4.dist-info/top_level.txt
beanstalk_dispatch-0.1.4.dist-info/RECORD
